influxLogger/__init__.py
influxLogger/influxLogger.py
influxLogger/tests/__init__.py
influxLogger/tests/test.py
influxLogger/tests/test2.py
influxLogger-0.0.3.dist-info/LICENSE
influxLogger-0.0.3.dist-info/METADATA
influxLogger-0.0.3.dist-info/WHEEL
influxLogger-0.0.3.dist-info/top_level.txt
influxLogger-0.0.3.dist-info/RECORD
